thelogger/__dirty_timer.py
thelogger/__init__.py
thelogger/__logger.py
thelogger/__sys_meta.py
thelogger/__ver.py
thelogger/__notify/__init__.py
thelogger/__notify/decorator.py
thelogger/__notify/exec_func.py
thelogger-0.4.3.dist-info/LICENSE
thelogger-0.4.3.dist-info/METADATA
thelogger-0.4.3.dist-info/WHEEL
thelogger-0.4.3.dist-info/top_level.txt
thelogger-0.4.3.dist-info/RECORD
