Metadata-Version: 2.1
Name: thelogger
Version: 0.4.3
Summary: Easy logging, timing and email notifications of code execution.
Home-page: UNKNOWN
License: Apache 2.0
Keywords: log,logging,logger,email,timimg,notification
Platform: UNKNOWN
Classifier: Development Status :: 3 - Alpha
Classifier: Intended Audience :: Developers
Classifier: Topic :: Software Development :: Build Tools
Classifier: License :: OSI Approved :: MIT License
Classifier: Programming Language :: Python :: 3
Classifier: Programming Language :: Python :: 3.4
Classifier: Programming Language :: Python :: 3.5
Classifier: Programming Language :: Python :: 3.6
Requires-Python: >3.8
License-File: LICENSE
Requires-Dist: pandas
Requires-Dist: tabulate
Requires-Dist: pytz
Requires-Dist: psutil
Requires-Dist: tzlocal
Requires-Dist: importlib-metadata (>=1.0) ; python_version < "3.8"
